mazeexplorer/__init__.py
mazeexplorer/compile_acs.py
mazeexplorer/config_template.txt
mazeexplorer/maze.py
mazeexplorer/mazeexplorer.py
mazeexplorer/script_manipulator.py
mazeexplorer/vizdoom_gym.py
mazeexplorer/wad.py
mazeexplorer/acc/Makefile
mazeexplorer/acc/acc.c
mazeexplorer/acc/acc.dsp
mazeexplorer/acc/acc.dsw
mazeexplorer/acc/common.h
mazeexplorer/acc/error.c
mazeexplorer/acc/error.h
mazeexplorer/acc/misc.c
mazeexplorer/acc/misc.h
mazeexplorer/acc/parse.c
mazeexplorer/acc/parse.h
mazeexplorer/acc/pcode.c
mazeexplorer/acc/pcode.h
mazeexplorer/acc/readme.md
mazeexplorer/acc/strlist.c
mazeexplorer/acc/strlist.h
mazeexplorer/acc/symbol.c
mazeexplorer/acc/symbol.h
mazeexplorer/acc/token.c
mazeexplorer/acc/token.h
mazeexplorer/acc/zcommon.acs
mazeexplorer/acc/zdefs.acs
mazeexplorer/acc/zspecial.acs
mazeexplorer/acc/zwvars.acs
mazeexplorer/content/acs_template.txt
mazeexplorer/content/doom_textures.txt
mazeexplorer-1.0.4.dist-info/LICENSE
mazeexplorer-1.0.4.dist-info/METADATA
mazeexplorer-1.0.4.dist-info/NOTICE.txt
mazeexplorer-1.0.4.dist-info/WHEEL
mazeexplorer-1.0.4.dist-info/top_level.txt
mazeexplorer-1.0.4.dist-info/RECORD
