Metadata-Version: 2.1
Name: mazeexplorer
Version: 1.0.4
Summary: Customisable 3D benchmark for assessing generalisation in Reinforcement Learning.
Home-page: https://github.com/microsoft/MazeExplorer
Author: Luke Harries, Sebastian Lee, Jaroslaw Rzepecki, Katya Hofmann, Sam Devlin
Author-email: sam.devlin@microsoft.com
License: UNKNOWN
Platform: UNKNOWN
Classifier: Programming Language :: Python :: 3
Classifier: License :: OSI Approved :: MIT License
Classifier: Operating System :: OS Independent
Requires-Dist: vizdoom
Requires-Dist: gym
Requires-Dist: omgifol
Requires-Dist: opencv-python
Requires-Dist: imageio
Requires-Dist: numpy
Requires-Dist: tensorboardX
Requires-Dist: pytest
